pymoises/Transactions.py
pymoises/__init__.py
pymoises/bussinesUnits.py
pymoises/customer.py
pymoises/psps.py
pymoises/dto/__init__.py
pymoises/dto/input/__init__.py
pymoises/dto/input/customer/__init__.py
pymoises/dto/input/customer/checkEmailPhone_customer_input_dto.py
pymoises/dto/input/customer/createLead_input_dto.py
pymoises/dto/input/transaction/__init__.py
pymoises/dto/input/transaction/create_transaction_input_dto.py
pymoises/dto/output/__init__.py
pymoises/dto/output/customer/__init__.py
pymoises/dto/output/customer/createLead_output_dto.py
pymoises/dto/output/customer/customer_output_dto.py
pymoises/dto/output/customer/moveLead_output_dto.py
pymoises/dto/output/psps/__init__.py
pymoises/dto/output/psps/get_info_psp_output_dto.py
pymoises/dto/output/transaction/__init__.py
pymoises/dto/output/transaction/transaction_output_dto.py
pymoises-1.1.19.dist-info/METADATA
pymoises-1.1.19.dist-info/WHEEL
pymoises-1.1.19.dist-info/top_level.txt
pymoises-1.1.19.dist-info/RECORD
